{
  "metadata": {
    "source": "Open-Meteo Historical Weather API (ERA5 reanalysis)",
    "provider": "Open-Meteo.com / ECMWF ERA5",
    "region": "European Alps \u2014 representative stations",
    "period": "2000-2024",
    "variables": [
      "temperature_2m_mean",
      "snowfall_sum",
      "snow_depth"
    ],
    "stations": {
      "Low Alps (< 1500m)": [
        "Innsbruck",
        "Bolzano",
        "Garmisch",
        "Grenoble",
        "Salzburg"
      ],
      "Mid Alps (1500-2500m)": [
        "Davos",
        "St. Moritz",
        "Lech",
        "Zermatt",
        "Cortina"
      ],
      "High Alps (> 2500m)": [
        "Jungfraujoch",
        "Zugspitze",
        "Sonnblick",
        "Weissfluhjoch"
      ]
    },
    "generated": "2026-03-27T21:07:44.332648"
  },
  "elevation_bands": {
    "Low Alps (< 1500m)": {
      "years": [
        2000,
        2001,
        2002,
        2003,
        2004,
        2005,
        2006,
        2007,
        2008,
        2009,
        2010,
        2011,
        2012,
        2013,
        2014,
        2015,
        2016,
        2017,
        2018,
        2019,
        2020,
        2021,
        2022,
        2023,
        2024
      ],
      "snow_days": [
        153.0,
        160.3,
        142.0,
        164.3,
        176.3,
        150.7,
        169.3,
        133.0,
        171.0,
        190.3,
        188.7,
        114.0,
        174.0,
        179.0,
        145.7,
        131.0,
        131.3,
        120.7,
        120.3,
        157.0,
        105.0,
        150.3,
        110.7,
        112.7,
        108.3
      ],
      "trend_line": [
        153.0,
        150.8,
        148.7,
        146.5,
        144.4,
        142.2,
        140.0,
        137.9,
        135.7,
        133.6,
        131.4,
        129.2,
        127.1,
        124.9,
        122.8,
        120.6,
        118.4,
        116.3,
        114.1,
        112.0,
        109.8,
        107.6,
        105.5,
        103.3,
        101.2
      ],
      "mann_kendall": {
        "trend": "decreasing",
        "p_value": 0.005449,
        "slope": -21.6,
        "significance": "Highly Significant",
        "direction": "Declining"
      },
      "change_point": {
        "change_point_index": 13,
        "p_value": 0.0068,
        "before_mean": 161.9,
        "after_mean": 126.6,
        "year": 2013
      },
      "correlation": {
        "r": -0.828,
        "r_squared": 0.685,
        "p_value": 0.0
      },
      "projections": {
        "Current Trend": {
          "years": [
            2025,
            2026,
            2027,
            2028,
            2029,
            2030,
            2031,
            2032,
            2033,
            2034,
            2035,
            2036,
            2037,
            2038,
            2039,
            2040,
            2041,
            2042,
            2043,
            2044,
            2045,
            2046,
            2047,
            2048,
            2049,
            2050
          ],
          "values": [
            106.2,
            104.1,
            102.0,
            99.9,
            97.8,
            95.7,
            93.6,
            91.4,
            89.3,
            87.2,
            85.1,
            83.0,
            80.9,
            78.8,
            76.7,
            74.6,
            72.5,
            70.4,
            68.3,
            66.2,
            64.1,
            62.0,
            59.8,
            57.7,
            55.6,
            53.5
          ],
          "upper_ci": [
            148.4,
            147.1,
            145.7,
            144.4,
            143.1,
            141.7,
            140.3,
            139.0,
            137.6,
            136.2,
            134.8,
            133.3,
            131.9,
            130.5,
            129.0,
            127.6,
            126.1,
            124.6,
            123.1,
            121.7,
            120.2,
            118.7,
            117.2,
            115.6,
            114.1,
            112.6
          ],
          "lower_ci": [
            64.0,
            61.1,
            58.2,
            55.3,
            52.5,
            49.6,
            46.8,
            43.9,
            41.1,
            38.3,
            35.5,
            32.7,
            29.9,
            27.2,
            24.4,
            21.6,
            18.9,
            16.1,
            13.4,
            10.7,
            8.0,
            5.3,
            2.5,
            0,
            0,
            0
          ],
          "loss_by_2050": -54.8,
          "snow_days_2050": 53.5
        },
        "Accelerated (RCP 8.5)": {
          "years": [
            2025,
            2026,
            2027,
            2028,
            2029,
            2030,
            2031,
            2032,
            2033,
            2034,
            2035,
            2036,
            2037,
            2038,
            2039,
            2040,
            2041,
            2042,
            2043,
            2044,
            2045,
            2046,
            2047,
            2048,
            2049,
            2050
          ],
          "values": [
            105.1,
            102.0,
            98.8,
            95.7,
            92.5,
            89.3,
            86.2,
            83.0,
            79.9,
            76.7,
            73.5,
            70.4,
            67.2,
            64.1,
            60.9,
            57.7,
            54.6,
            51.4,
            48.3,
            45.1,
            41.9,
            38.8,
            35.6,
            32.5,
            29.3,
            26.1
          ],
          "upper_ci": [
            147.3,
            145.0,
            142.6,
            140.2,
            137.8,
            135.4,
            133.0,
            130.5,
            128.1,
            125.6,
            123.2,
            120.7,
            118.2,
            115.7,
            113.2,
            110.7,
            108.2,
            105.7,
            103.1,
            100.6,
            98.0,
            95.5,
            92.9,
            90.4,
            87.8,
            85.2
          ],
          "lower_ci": [
            63.0,
            59.0,
            55.1,
            51.1,
            47.2,
            43.3,
            39.4,
            35.5,
            31.6,
            27.8,
            23.9,
            20.1,
            16.2,
            12.4,
            8.6,
            4.8,
            1.0,
            0,
            0,
            0,
            0,
            0,
            0,
            0,
            0,
            0
          ],
          "loss_by_2050": -82.2,
          "snow_days_2050": 26.1
        },
        "Paris-Aligned (RCP 2.6)": {
          "years": [
            2025,
            2026,
            2027,
            2028,
            2029,
            2030,
            2031,
            2032,
            2033,
            2034,
            2035,
            2036,
            2037,
            2038,
            2039,
            2040,
            2041,
            2042,
            2043,
            2044,
            2045,
            2046,
            2047,
            2048,
            2049,
            2050
          ],
          "values": [
            107.0,
            105.8,
            104.5,
            103.2,
            102.0,
            100.7,
            99.5,
            98.2,
            96.9,
            95.7,
            94.4,
            93.1,
            91.9,
            90.6,
            89.3,
            88.1,
            86.8,
            85.5,
            84.3,
            83.0,
            81.8,
            80.5,
            79.2,
            78.0,
            76.7,
            75.4
          ],
          "upper_ci": [
            149.2,
            148.8,
            148.3,
            147.8,
            147.3,
            146.8,
            146.2,
            145.7,
            145.2,
            144.6,
            144.0,
            143.4,
            142.9,
            142.3,
            141.7,
            141.0,
            140.4,
            139.8,
            139.2,
            138.5,
            137.9,
            137.2,
            136.5,
            135.9,
            135.2,
            134.5
          ],
          "lower_ci": [
            64.9,
            62.8,
            60.7,
            58.7,
            56.7,
            54.7,
            52.7,
            50.7,
            48.7,
            46.7,
            44.8,
            42.8,
            40.9,
            39.0,
            37.0,
            35.1,
            33.2,
            31.3,
            29.4,
            27.5,
            25.7,
            23.8,
            21.9,
            20.1,
            18.2,
            16.4
          ],
          "loss_by_2050": -32.9,
          "snow_days_2050": 75.4
        }
      }
    },
    "Mid Alps (1500-2500m)": {
      "years": [
        2000,
        2001,
        2002,
        2003,
        2004,
        2005,
        2006,
        2007,
        2008,
        2009,
        2010,
        2011,
        2012,
        2013,
        2014,
        2015,
        2016,
        2017,
        2018,
        2019,
        2020,
        2021,
        2022,
        2023,
        2024
      ],
      "snow_days": [
        300.0,
        352.7,
        325.7,
        310.3,
        333.3,
        269.3,
        270.0,
        286.7,
        313.0,
        318.3,
        329.0,
        289.0,
        318.7,
        333.3,
        312.3,
        309.7,
        300.0,
        314.0,
        296.7,
        340.7,
        324.7,
        332.0,
        274.7,
        283.0,
        343.7
      ],
      "trend_line": [
        300.0,
        300.3,
        300.6,
        300.9,
        301.2,
        301.5,
        301.8,
        302.1,
        302.4,
        302.7,
        303.0,
        303.3,
        303.6,
        303.9,
        304.2,
        304.5,
        304.8,
        305.2,
        305.5,
        305.8,
        306.1,
        306.4,
        306.7,
        307.0,
        307.3
      ],
      "mann_kendall": {
        "trend": "no trend",
        "p_value": 0.761295,
        "slope": 3.03,
        "significance": "Not Significant",
        "direction": "Increasing"
      },
      "change_point": {
        "change_point_index": 4,
        "p_value": 1.0,
        "before_mean": 324.4,
        "after_mean": 307.9,
        "year": 2004
      },
      "correlation": {
        "r": -0.118,
        "r_squared": 0.014,
        "p_value": 0.575395
      },
      "projections": {
        "Current Trend": {
          "years": [
            2025,
            2026,
            2027,
            2028,
            2029,
            2030,
            2031,
            2032,
            2033,
            2034,
            2035,
            2036,
            2037,
            2038,
            2039,
            2040,
            2041,
            2042,
            2043,
            2044,
            2045,
            2046,
            2047,
            2048,
            2049,
            2050
          ],
          "values": [
            343.8,
            343.9,
            343.9,
            344.0,
            344.1,
            344.2,
            344.3,
            344.3,
            344.4,
            344.5,
            344.6,
            344.7,
            344.7,
            344.8,
            344.9,
            345.0,
            345.1,
            345.1,
            345.2,
            345.3,
            345.4,
            345.5,
            345.5,
            345.6,
            345.7,
            345.8
          ],
          "upper_ci": [
            389.4,
            390.3,
            391.3,
            392.2,
            393.1,
            394.0,
            394.9,
            395.7,
            396.6,
            397.4,
            398.2,
            399.1,
            399.9,
            400.7,
            401.5,
            402.3,
            403.0,
            403.8,
            404.5,
            405.3,
            406.0,
            406.8,
            407.5,
            408.2,
            408.9,
            409.7
          ],
          "lower_ci": [
            298.2,
            297.4,
            296.6,
            295.9,
            295.1,
            294.4,
            293.7,
            293.0,
            292.3,
            291.6,
            290.9,
            290.3,
            289.6,
            289.0,
            288.3,
            287.7,
            287.1,
            286.5,
            285.9,
            285.3,
            284.7,
            284.1,
            283.6,
            283.0,
            282.4,
            281.9
          ],
          "loss_by_2050": 2.1,
          "snow_days_2050": 345.8
        },
        "Accelerated (RCP 8.5)": {
          "years": [
            2025,
            2026,
            2027,
            2028,
            2029,
            2030,
            2031,
            2032,
            2033,
            2034,
            2035,
            2036,
            2037,
            2038,
            2039,
            2040,
            2041,
            2042,
            2043,
            2044,
            2045,
            2046,
            2047,
            2048,
            2049,
            2050
          ],
          "values": [
            343.8,
            343.9,
            344.1,
            344.2,
            344.3,
            344.4,
            344.5,
            344.7,
            344.8,
            344.9,
            345.0,
            345.1,
            345.3,
            345.4,
            345.5,
            345.6,
            345.7,
            345.9,
            346.0,
            346.1,
            346.2,
            346.3,
            346.5,
            346.6,
            346.7,
            346.8
          ],
          "upper_ci": [
            389.4,
            390.4,
            391.4,
            392.3,
            393.3,
            394.2,
            395.1,
            396.0,
            396.9,
            397.8,
            398.7,
            399.5,
            400.4,
            401.2,
            402.1,
            402.9,
            403.7,
            404.5,
            405.3,
            406.1,
            406.9,
            407.7,
            408.4,
            409.2,
            409.9,
            410.7
          ],
          "lower_ci": [
            298.2,
            297.5,
            296.7,
            296.0,
            295.3,
            294.6,
            293.9,
            293.3,
            292.6,
            292.0,
            291.4,
            290.7,
            290.1,
            289.5,
            288.9,
            288.3,
            287.8,
            287.2,
            286.6,
            286.1,
            285.6,
            285.0,
            284.5,
            284.0,
            283.4,
            282.9
          ],
          "loss_by_2050": 3.1,
          "snow_days_2050": 346.8
        },
        "Paris-Aligned (RCP 2.6)": {
          "years": [
            2025,
            2026,
            2027,
            2028,
            2029,
            2030,
            2031,
            2032,
            2033,
            2034,
            2035,
            2036,
            2037,
            2038,
            2039,
            2040,
            2041,
            2042,
            2043,
            2044,
            2045,
            2046,
            2047,
            2048,
            2049,
            2050
          ],
          "values": [
            343.7,
            343.8,
            343.8,
            343.9,
            343.9,
            344.0,
            344.0,
            344.1,
            344.1,
            344.2,
            344.2,
            344.3,
            344.3,
            344.4,
            344.4,
            344.5,
            344.5,
            344.6,
            344.6,
            344.7,
            344.7,
            344.8,
            344.8,
            344.8,
            344.9,
            344.9
          ],
          "upper_ci": [
            389.4,
            390.3,
            391.2,
            392.1,
            392.9,
            393.8,
            394.6,
            395.5,
            396.3,
            397.1,
            397.9,
            398.7,
            399.5,
            400.2,
            401.0,
            401.7,
            402.5,
            403.2,
            403.9,
            404.7,
            405.4,
            406.1,
            406.8,
            407.5,
            408.1,
            408.8
          ],
          "lower_ci": [
            298.1,
            297.3,
            296.5,
            295.7,
            294.9,
            294.2,
            293.4,
            292.7,
            292.0,
            291.3,
            290.6,
            289.9,
            289.2,
            288.5,
            287.8,
            287.2,
            286.5,
            285.9,
            285.3,
            284.7,
            284.0,
            283.4,
            282.8,
            282.2,
            281.7,
            281.1
          ],
          "loss_by_2050": 1.2,
          "snow_days_2050": 344.9
        }
      }
    },
    "High Alps (> 2500m)": {
      "years": [
        2000,
        2001,
        2002,
        2003,
        2004,
        2005,
        2006,
        2007,
        2008,
        2009,
        2010,
        2011,
        2012,
        2013,
        2014,
        2015,
        2016,
        2017,
        2018,
        2019,
        2020,
        2021,
        2022,
        2023,
        2024
      ],
      "snow_days": [
        364.7,
        365.0,
        365.0,
        365.0,
        366.0,
        365.0,
        365.0,
        365.0,
        366.0,
        365.0,
        365.0,
        365.0,
        366.0,
        365.0,
        365.0,
        365.0,
        366.0,
        365.0,
        365.0,
        365.0,
        366.0,
        365.0,
        365.0,
        365.0,
        366.0
      ],
      "trend_line": [
        364.7,
        364.7,
        364.7,
        364.7,
        364.7,
        364.7,
        364.7,
        364.7,
        364.7,
        364.7,
        364.7,
        364.7,
        364.7,
        364.7,
        364.7,
        364.7,
        364.7,
        364.7,
        364.7,
        364.7,
        364.7,
        364.7,
        364.7,
        364.7,
        364.7
      ],
      "mann_kendall": {
        "trend": "no trend",
        "p_value": 0.218052,
        "slope": 0.0,
        "significance": "Not Significant",
        "direction": "Increasing"
      },
      "change_point": {
        "change_point_index": 3,
        "year": 2003,
        "p_value": 1.0,
        "before_mean": 364.9,
        "after_mean": 365.3
      },
      "correlation": {
        "r": 0.108,
        "r_squared": 0.012,
        "p_value": 0.606861
      },
      "projections": {
        "Current Trend": {
          "years": [
            2025,
            2026,
            2027,
            2028,
            2029,
            2030,
            2031,
            2032,
            2033,
            2034,
            2035,
            2036,
            2037,
            2038,
            2039,
            2040,
            2041,
            2042,
            2043,
            2044,
            2045,
            2046,
            2047,
            2048,
            2049,
            2050
          ],
          "values": [
            366.0,
            366.0,
            366.0,
            366.0,
            366.1,
            366.1,
            366.1,
            366.1,
            366.1,
            366.1,
            366.1,
            366.1,
            366.2,
            366.2,
            366.2,
            366.2,
            366.2,
            366.2,
            366.2,
            366.2,
            366.3,
            366.3,
            366.3,
            366.3,
            366.3,
            366.3
          ],
          "upper_ci": [
            366.9,
            366.9,
            366.9,
            367.0,
            367.0,
            367.0,
            367.0,
            367.1,
            367.1,
            367.1,
            367.1,
            367.2,
            367.2,
            367.2,
            367.2,
            367.3,
            367.3,
            367.3,
            367.3,
            367.4,
            367.4,
            367.4,
            367.4,
            367.5,
            367.5,
            367.5
          ],
          "lower_ci": [
            365.2,
            365.1,
            365.1,
            365.1,
            365.1,
            365.1,
            365.1,
            365.1,
            365.1,
            365.1,
            365.1,
            365.1,
            365.1,
            365.1,
            365.1,
            365.1,
            365.1,
            365.1,
            365.1,
            365.1,
            365.1,
            365.1,
            365.1,
            365.1,
            365.1,
            365.1
          ],
          "loss_by_2050": 0.3,
          "snow_days_2050": 366.3
        },
        "Accelerated (RCP 8.5)": {
          "years": [
            2025,
            2026,
            2027,
            2028,
            2029,
            2030,
            2031,
            2032,
            2033,
            2034,
            2035,
            2036,
            2037,
            2038,
            2039,
            2040,
            2041,
            2042,
            2043,
            2044,
            2045,
            2046,
            2047,
            2048,
            2049,
            2050
          ],
          "values": [
            366.0,
            366.0,
            366.1,
            366.1,
            366.1,
            366.1,
            366.1,
            366.1,
            366.2,
            366.2,
            366.2,
            366.2,
            366.2,
            366.3,
            366.3,
            366.3,
            366.3,
            366.3,
            366.3,
            366.4,
            366.4,
            366.4,
            366.4,
            366.4,
            366.4,
            366.5
          ],
          "upper_ci": [
            366.9,
            366.9,
            366.9,
            367.0,
            367.0,
            367.0,
            367.1,
            367.1,
            367.1,
            367.2,
            367.2,
            367.2,
            367.3,
            367.3,
            367.3,
            367.4,
            367.4,
            367.4,
            367.5,
            367.5,
            367.5,
            367.5,
            367.6,
            367.6,
            367.6,
            367.7
          ],
          "lower_ci": [
            365.2,
            365.2,
            365.2,
            365.2,
            365.2,
            365.2,
            365.2,
            365.2,
            365.2,
            365.2,
            365.2,
            365.2,
            365.2,
            365.2,
            365.2,
            365.2,
            365.2,
            365.2,
            365.2,
            365.2,
            365.2,
            365.2,
            365.2,
            365.3,
            365.3,
            365.3
          ],
          "loss_by_2050": 0.5,
          "snow_days_2050": 366.5
        },
        "Paris-Aligned (RCP 2.6)": {
          "years": [
            2025,
            2026,
            2027,
            2028,
            2029,
            2030,
            2031,
            2032,
            2033,
            2034,
            2035,
            2036,
            2037,
            2038,
            2039,
            2040,
            2041,
            2042,
            2043,
            2044,
            2045,
            2046,
            2047,
            2048,
            2049,
            2050
          ],
          "values": [
            366.0,
            366.0,
            366.0,
            366.0,
            366.0,
            366.0,
            366.1,
            366.1,
            366.1,
            366.1,
            366.1,
            366.1,
            366.1,
            366.1,
            366.1,
            366.1,
            366.1,
            366.1,
            366.1,
            366.1,
            366.2,
            366.2,
            366.2,
            366.2,
            366.2,
            366.2
          ],
          "upper_ci": [
            366.9,
            366.9,
            366.9,
            366.9,
            367.0,
            367.0,
            367.0,
            367.0,
            367.0,
            367.1,
            367.1,
            367.1,
            367.1,
            367.2,
            367.2,
            367.2,
            367.2,
            367.2,
            367.3,
            367.3,
            367.3,
            367.3,
            367.3,
            367.4,
            367.4,
            367.4
          ],
          "lower_ci": [
            365.1,
            365.1,
            365.1,
            365.1,
            365.1,
            365.1,
            365.1,
            365.1,
            365.1,
            365.1,
            365.1,
            365.1,
            365.1,
            365.1,
            365.0,
            365.0,
            365.0,
            365.0,
            365.0,
            365.0,
            365.0,
            365.0,
            365.0,
            365.0,
            365.0,
            365.0
          ],
          "loss_by_2050": 0.2,
          "snow_days_2050": 366.2
        }
      }
    }
  },
  "surface_3d": {
    "years": [
      2000,
      2001,
      2002,
      2003,
      2004,
      2005,
      2006,
      2007,
      2008,
      2009,
      2010,
      2011,
      2012,
      2013,
      2014,
      2015,
      2016,
      2017,
      2018,
      2019,
      2020,
      2021,
      2022,
      2023,
      2024
    ],
    "months": [
      1,
      2,
      3,
      4,
      5,
      6,
      7,
      8,
      9,
      10,
      11,
      12
    ],
    "z": [
      [
        0.52,
        0.94,
        1.38,
        0.62,
        0.15,
        0.01,
        0.28,
        0.02,
        0.11,
        0.61,
        1.48,
        0.48
      ],
      [
        0.87,
        0.96,
        1.08,
        1.32,
        0.06,
        0.31,
        0.01,
        0.0,
        0.41,
        0.04,
        0.79,
        0.6
      ],
      [
        0.13,
        0.87,
        0.72,
        0.47,
        0.47,
        0.01,
        0.0,
        0.02,
        0.32,
        0.28,
        1.54,
        0.6
      ],
      [
        0.65,
        0.44,
        0.19,
        0.51,
        0.22,
        0.0,
        0.0,
        0.01,
        0.03,
        0.88,
        0.82,
        0.71
      ],
      [
        1.01,
        0.71,
        0.7,
        0.53,
        0.43,
        0.08,
        0.06,
        0.0,
        0.11,
        0.22,
        0.46,
        0.47
      ],
      [
        0.65,
        0.78,
        0.31,
        0.65,
        0.35,
        0.02,
        0.05,
        0.02,
        0.1,
        0.19,
        0.39,
        0.88
      ],
      [
        0.47,
        0.7,
        0.87,
        0.67,
        0.27,
        0.14,
        0.0,
        0.09,
        0.0,
        0.05,
        0.43,
        0.62
      ],
      [
        0.63,
        0.58,
        0.83,
        0.05,
        0.53,
        0.1,
        0.03,
        0.0,
        0.48,
        0.18,
        1.12,
        0.62
      ],
      [
        0.68,
        0.29,
        0.95,
        1.2,
        0.16,
        0.03,
        0.04,
        0.01,
        0.09,
        0.58,
        0.87,
        1.02
      ],
      [
        0.46,
        1.21,
        1.22,
        0.4,
        0.08,
        0.07,
        0.07,
        0.0,
        0.01,
        0.52,
        0.82,
        0.85
      ],
      [
        0.42,
        0.66,
        0.55,
        0.38,
        0.61,
        0.18,
        0.0,
        0.23,
        0.26,
        0.61,
        0.92,
        0.86
      ],
      [
        0.3,
        0.41,
        0.3,
        0.15,
        0.24,
        0.08,
        0.06,
        0.03,
        0.31,
        0.48,
        0.04,
        1.29
      ],
      [
        1.52,
        0.43,
        0.37,
        0.92,
        0.21,
        0.19,
        0.0,
        0.07,
        0.12,
        0.52,
        0.78,
        0.94
      ],
      [
        0.7,
        0.82,
        0.76,
        0.54,
        0.66,
        0.26,
        0.0,
        0.01,
        0.11,
        0.49,
        0.94,
        0.61
      ],
      [
        0.96,
        1.04,
        0.6,
        0.42,
        0.35,
        0.04,
        0.03,
        0.01,
        0.03,
        0.43,
        0.88,
        0.62
      ],
      [
        0.96,
        0.5,
        0.67,
        0.54,
        0.53,
        0.02,
        0.0,
        0.0,
        0.15,
        0.38,
        0.29,
        0.08
      ],
      [
        0.81,
        1.1,
        0.76,
        0.81,
        0.58,
        0.06,
        0.05,
        0.02,
        0.01,
        0.15,
        0.65,
        0.07
      ],
      [
        0.64,
        0.61,
        0.6,
        0.85,
        0.34,
        0.02,
        0.01,
        0.01,
        0.51,
        0.34,
        0.93,
        1.21
      ],
      [
        1.36,
        0.42,
        0.67,
        0.17,
        0.12,
        0.0,
        0.0,
        0.02,
        0.03,
        0.64,
        0.25,
        0.98
      ],
      [
        1.59,
        0.61,
        0.78,
        0.81,
        0.75,
        0.0,
        0.01,
        0.0,
        0.14,
        0.19,
        1.17,
        0.86
      ],
      [
        0.35,
        0.97,
        0.62,
        0.12,
        0.22,
        0.11,
        0.0,
        0.04,
        0.2,
        0.68,
        0.09,
        1.08
      ],
      [
        1.34,
        0.4,
        0.71,
        0.46,
        0.64,
        0.0,
        0.01,
        0.02,
        0.02,
        0.15,
        0.84,
        0.67
      ],
      [
        0.5,
        1.22,
        0.05,
        0.49,
        0.1,
        0.01,
        0.0,
        0.0,
        0.23,
        0.05,
        0.47,
        0.47
      ],
      [
        0.49,
        0.52,
        0.71,
        0.83,
        0.23,
        0.0,
        0.01,
        0.04,
        0.09,
        0.24,
        1.26,
        1.42
      ],
      [
        0.6,
        0.57,
        0.82,
        0.86,
        0.37,
        0.1,
        0.0,
        0.0,
        0.32,
        0.14,
        0.36,
        0.62
      ]
    ]
  }
}